setup.cfg
setup.py
spojsol/__init__.py
spojsol/spojsol.py
spojsol.egg-info/PKG-INFO
spojsol.egg-info/SOURCES.txt
spojsol.egg-info/dependency_links.txt
spojsol.egg-info/entry_points.txt
spojsol.egg-info/requires.txt
spojsol.egg-info/top_level.txt