Metadata-Version: 1.1
Name: spojsol
Version: 0.1
Summary: Download your spoj solutions
Home-page: https://github.com/codenirvana/spoj-solutions
Author: Udit Vasu
Author-email: admin@codenirvana.in
License: MIT
Keywords: spoj solutions command line tool
Platform: UNKNOWN
Classifier: Development Status :: 4 - Beta
Classifier: Intended Audience :: Developers
Classifier: License :: OSI Approved :: MIT License
Classifier: Programming Language :: Python
Classifier: Programming Language :: Python :: 2
Classifier: Programming Language :: Python :: 2.7
Classifier: Programming Language :: Python :: 3
Classifier: Programming Language :: Python :: 3.3
Classifier: Programming Language :: Python :: 3.4
Classifier: Programming Language :: Python :: 3.5
Classifier: Topic :: Internet
Classifier: Topic :: Utilities
